rasa_mongo_tracker_store/__init__.py
rasa_mongo_tracker_store/store.py
rasa_mongo_tracker_store-0.1.1.dist-info/METADATA
rasa_mongo_tracker_store-0.1.1.dist-info/RECORD
rasa_mongo_tracker_store-0.1.1.dist-info/WHEEL
rasa_mongo_tracker_store-0.1.1.dist-info/top_level.txt
