Metadata-Version: 2.1
Name: rasa-mongo-tracker-store
Version: 0.1.1
Summary: TrackerStore for rasa_core connecting to MongoDB
Home-page: https://github.com/m90/rasa-mongo-tracker-store
Author: Frederik Ring
Author-email: frederik.ring@gmail.com
License: UNKNOWN
Platform: UNKNOWN
Classifier: Programming Language :: Python :: 3
Classifier: License :: OSI Approved :: MIT License
Classifier: Operating System :: OS Independent
Requires-Dist: dialogflow (~=0.4)
Requires-Dist: pymongo (~=3.7)
